{
  "id": "vision-lab",
  "name": "Vision Lab",
  "type": "vision",
  "repoUrl": "https://github.com/ntc-ai/vision-lab",
  "description": "Detection, segmentation and captioning pipelines.",
  "tags": [
    "yolo",
    "sam",
    "caption"
  ],
  "accentColor": "#22d3ee",
  "visual": {
    "imageUrl": "/assets/projects/vision-lab.jpg",
    "focus": "62% 72%",
    "ambient": "#0284c7",
    "ambientSoft": "#061f35"
  },
  "installStatus": "installed",
  "runStatus": "stopped",
  "requirements": {
    "minimum": {
      "cpuCores": 6,
      "ramMb": 12288,
      "vramMb": 6144,
      "diskGb": 18,
      "gpuRequired": true
    },
    "recommended": {
      "cpuCores": 10,
      "ramMb": 24576,
      "vramMb": 12288,
      "diskGb": 32,
      "gpuRequired": true
    }
  },
  "editableConfig": {
    "profile": "Realtime 1080p",
    "branch": "stable",
    "port": 8077,
    "installDirectory": "D:/AIHub/providers/vision-lab"
  },
  "lastBenchmark": {
    "headlineMetric": "58 FPS",
    "secondaryMetric": "p95 34 ms",
    "latencyMs": 34,
    "throughput": 58,
    "vramPeakMb": 10450,
    "measuredAt": "2026-05-10T09:12:00.000Z"
  },
  "lastRunAt": "2026-05-10T09:12:00.000Z",
  "runtime": {
    "defaultPort": 8077,
    "healthUrl": "http://localhost:8077/health",
    "metricsUrl": "http://localhost:8077/metrics"
  },
  "commands": {
    "windows": {
      "setup": "scripts/windows/setup.ps1",
      "run": "scripts/windows/run.ps1",
      "stop": "scripts/windows/stop.ps1",
      "health": "scripts/windows/health.ps1",
      "metrics": "scripts/windows/collect-metrics.ps1"
    },
    "linux": {
      "setup": "scripts/linux/setup.sh",
      "run": "scripts/linux/run.sh",
      "stop": "scripts/linux/stop.sh",
      "health": "scripts/linux/health.sh",
      "metrics": "scripts/linux/collect-metrics.sh"
    }
  },
  "compatibility": {
    "level": "green",
    "reasons": [
      "Hardware has enough resources for the recommended profile."
    ]
  }
}
